done_script/__init__.py
done_script/python_standard/__init__.py
done_script/python_standard/cls_decorate_demo.py
done_script/python_standard/collection_deque_demo.py
done_script/python_standard/copy_deepcopy_demo.py
done_script/python_standard/decorator_advanced.py
done_script/python_standard/decorator_demo.py
done_script/python_standard/descriptor_demo.py
done_script/python_standard/enum_demo.py
done_script/python_standard/exception_demo.py
done_script/python_standard/exec_eval_ast_demo.py
done_script/python_standard/func_limit_params.py
done_script/python_standard/generator_demo.py
done_script/python_standard/import_module_demo.py
done_script/python_standard/lambda_demo.py
done_script/python_standard/namedtuple_demo.py
done_script/python_standard/package_init_demo.py
done_script/python_standard/partial_func_demo.py
done_script/python_standard/unpack_operator.py
done_script/python_standard/my_package/__init__.py
done_script/python_standard/my_package/demo_1.py
done_script/python_standard/my_package/demo_2.py
done_script/python_standard/object_oriented/__init__.py
done_script/python_standard/object_oriented/access_private_demo.py
done_script/python_standard/object_oriented/attribute_demo.py
done_script/python_standard/object_oriented/class_method.py
done_script/python_standard/object_oriented/constructor_demo.py
done_script/python_standard/object_oriented/magic_method_demo.py
done_script/python_standard/object_oriented/mro_multi_inherit.py
done_script/python_standard/object_oriented/singleton_demo.py
done_script/python_standard/object_oriented/super_call_demo.py
drawing_overlap/__init__.py
drawing_overlap/draw_axes_global.py
yang_pypi-1.1.0.dist-info/METADATA
yang_pypi-1.1.0.dist-info/WHEEL
yang_pypi-1.1.0.dist-info/license_demo.py
yang_pypi-1.1.0.dist-info/top_level.txt
yang_pypi-1.1.0.dist-info/RECORD
