Metadata-Version: 2.1
Name: yang_pypi
Version: 1.1.0
Summary: 版本更新
Author: GuangZe
Author-email: 2127617756@qq.com
License-File: license_demo.py
Requires-Dist: loguru
